{
  "former_prefixes": null,
  "dataAccessProperties": null,
  "availableOnline": null,
  "confirmed": null,
  "dataAccessDetails": null,
  "datasetFeatures": null,
  "deprecated": null,
  "exampleIdentifiers": null,
  "guidanceOnLocatingIds": null,
  "opencorporates": null,
  "jurisdiction": [
    {
      "countryCode": "MW",
      "country": "Malawi"
    }
  ],
  "languages": null,
  "lastUpdated": null,
  "structure": null,
  "licenseDetails": null,
  "onlineAccessDetails": null,
  "licenseStatus": null,
  "registerType": null,
  "sector": null,
  "source": null,
  "subnational": null,
  "wikipedia": null,
  "code": "MW-CNM",
  "description": null,
  "name": "The Council for Non Governmental Organisations in Malawi",
  "publicDatabase": null,
  "url": "http://www.congoma.mw/index.html"
}